gh_scan_validator/__init__.py
gh_scan_validator/mls.py
gh_scan_validator-0.3.1.dist-info/METADATA
gh_scan_validator-0.3.1.dist-info/WHEEL
gh_scan_validator-0.3.1.dist-info/top_level.txt
gh_scan_validator-0.3.1.dist-info/RECORD
