Metadata-Version: 2.1
Name: gh-scan-validator
Version: 0.3.1
Summary: greeHill TSE Scan Validator
Home-page: UNKNOWN
Author: Geza Velkey
Author-email: geza.velkey@greehill.com
License: UNKNOWN
Platform: UNKNOWN
Classifier: Programming Language :: Python :: 3
Classifier: Programming Language :: Python :: 3.7
Classifier: Programming Language :: Python :: 3.8
Classifier: Programming Language :: Python :: 3.9
Classifier: Operating System :: OS Independent
Requires-Python: >=3.7
Requires-Dist: laspy
Requires-Dist: numpy
Requires-Dist: pandas
Requires-Dist: geopandas
Requires-Dist: matplotlib
Requires-Dist: coloredlogs
Requires-Dist: numba
Requires-Dist: scipy
Requires-Dist: Pillow
